<annotation>
	<folder>VOC2007</folder>
	<filename>Mall004_outdoor_617_normal.jpg</filename>
	<source>
		<database>The VOC2007 Database</database>
		<annotation>PASCAL VOC2007</annotation>
		<image>flickr</image>
		<flickrid>NULL</flickrid>
	</source>
	<owner>
		<flickrid>NULL</flickrid>
		<name>WH</name>
	</owner>
	<size>
		<width>1920</width>
		<height>1080</height>
		<depth>3</depth>
	</size>
		<segmented>0</segmented>
	<object>
		<name>person</name>
		<pose>Unspecified</pose>
		<truncated>1</truncated>
		<difficult>0</difficult>
		<bndbox>
			<xmin>235</xmin>
			<ymin>390</ymin>
			<xmax>310</xmax>
			<ymax>644</ymax>
		</bndbox>
	</object>
	<object>
		<name>person</name>
		<pose>Unspecified</pose>
		<truncated>1</truncated>
		<difficult>0</difficult>
		<bndbox>
			<xmin>629</xmin>
			<ymin>479</ymin>
			<xmax>718</xmax>
			<ymax>801</ymax>
		</bndbox>
	</object>
	<object>
		<name>person</name>
		<pose>Unspecified</pose>
		<truncated>1</truncated>
		<difficult>0</difficult>
		<bndbox>
			<xmin>456</xmin>
			<ymin>411</ymin>
			<xmax>539</xmax>
			<ymax>542</ymax>
		</bndbox>
	</object>
	<object>
		<name>person</name>
		<pose>Unspecified</pose>
		<truncated>1</truncated>
		<difficult>0</difficult>
		<bndbox>
			<xmin>516</xmin>
			<ymin>397</ymin>
			<xmax>600</xmax>
			<ymax>533</ymax>
		</bndbox>
	</object>
	<object>
		<name>person</name>
		<pose>Unspecified</pose>
		<truncated>1</truncated>
		<difficult>0</difficult>
		<bndbox>
			<xmin>656</xmin>
			<ymin>342</ymin>
			<xmax>751</xmax>
			<ymax>466</ymax>
		</bndbox>
	</object>
	<object>
		<name>person</name>
		<pose>Unspecified</pose>
		<truncated>1</truncated>
		<difficult>0</difficult>
		<bndbox>
			<xmin>934</xmin>
			<ymin>230</ymin>
			<xmax>975</xmax>
			<ymax>378</ymax>
		</bndbox>
	</object>
	<object>
		<name>person</name>
		<pose>Unspecified</pose>
		<truncated>1</truncated>
		<difficult>0</difficult>
		<bndbox>
			<xmin>1358</xmin>
			<ymin>824</ymin>
			<xmax>1508</xmax>
			<ymax>1080</ymax>
		</bndbox>
	</object>
	<object>
		<name>person</name>
		<pose>Unspecified</pose>
		<truncated>1</truncated>
		<difficult>0</difficult>
		<bndbox>
			<xmin>1139</xmin>
			<ymin>702</ymin>
			<xmax>1275</xmax>
			<ymax>1080</ymax>
		</bndbox>
	</object>
	<object>
		<name>person</name>
		<pose>Unspecified</pose>
		<truncated>1</truncated>
		<difficult>0</difficult>
		<bndbox>
			<xmin>1478</xmin>
			<ymin>337</ymin>
			<xmax>1544</xmax>
			<ymax>533</ymax>
		</bndbox>
	</object>
	<object>
		<name>person</name>
		<pose>Unspecified</pose>
		<truncated>1</truncated>
		<difficult>0</difficult>
		<bndbox>
			<xmin>1444</xmin>
			<ymin>117</ymin>
			<xmax>1462</xmax>
			<ymax>174</ymax>
		</bndbox>
	</object>
	<object>
		<name>person</name>
		<pose>Unspecified</pose>
		<truncated>1</truncated>
		<difficult>0</difficult>
		<bndbox>
			<xmin>1430</xmin>
			<ymin>151</ymin>
			<xmax>1455</xmax>
			<ymax>239</ymax>
		</bndbox>
	</object>
	<object>
		<name>person</name>
		<pose>Unspecified</pose>
		<truncated>1</truncated>
		<difficult>0</difficult>
		<bndbox>
			<xmin>1457</xmin>
			<ymin>152</ymin>
			<xmax>1490</xmax>
			<ymax>242</ymax>
		</bndbox>
	</object>
	<object>
		<name>person</name>
		<pose>Unspecified</pose>
		<truncated>1</truncated>
		<difficult>0</difficult>
		<bndbox>
			<xmin>1565</xmin>
			<ymin>152</ymin>
			<xmax>1584</xmax>
			<ymax>212</ymax>
		</bndbox>
	</object>
	<object>
		<name>person</name>
		<pose>Unspecified</pose>
		<truncated>1</truncated>
		<difficult>0</difficult>
		<bndbox>
			<xmin>1654</xmin>
			<ymin>149</ymin>
			<xmax>1675</xmax>
			<ymax>222</ymax>
		</bndbox>
	</object>
	<object>
		<name>person</name>
		<pose>Unspecified</pose>
		<truncated>1</truncated>
		<difficult>0</difficult>
		<bndbox>
			<xmin>1547</xmin>
			<ymin>130</ymin>
			<xmax>1568</xmax>
			<ymax>194</ymax>
		</bndbox>
	</object>
	<object>
		<name>person</name>
		<pose>Unspecified</pose>
		<truncated>1</truncated>
		<difficult>0</difficult>
		<bndbox>
			<xmin>1570</xmin>
			<ymin>131</ymin>
			<xmax>1597</xmax>
			<ymax>198</ymax>
		</bndbox>
	</object>
	<object>
		<name>person</name>
		<pose>Unspecified</pose>
		<truncated>1</truncated>
		<difficult>0</difficult>
		<bndbox>
			<xmin>1653</xmin>
			<ymin>112</ymin>
			<xmax>1669</xmax>
			<ymax>157</ymax>
		</bndbox>
	</object>
	<object>
		<name>person</name>
		<pose>Unspecified</pose>
		<truncated>1</truncated>
		<difficult>0</difficult>
		<bndbox>
			<xmin>1630</xmin>
			<ymin>93</ymin>
			<xmax>1641</xmax>
			<ymax>124</ymax>
		</bndbox>
	</object>
	<object>
		<name>person</name>
		<pose>Unspecified</pose>
		<truncated>1</truncated>
		<difficult>0</difficult>
		<bndbox>
			<xmin>1690</xmin>
			<ymin>98</ymin>
			<xmax>1701</xmax>
			<ymax>131</ymax>
		</bndbox>
	</object>
	<object>
		<name>person</name>
		<pose>Unspecified</pose>
		<truncated>1</truncated>
		<difficult>0</difficult>
		<bndbox>
			<xmin>1699</xmin>
			<ymin>102</ymin>
			<xmax>1708</xmax>
			<ymax>130</ymax>
		</bndbox>
	</object>
	<object>
		<name>person</name>
		<pose>Unspecified</pose>
		<truncated>1</truncated>
		<difficult>0</difficult>
		<bndbox>
			<xmin>1882</xmin>
			<ymin>114</ymin>
			<xmax>1892</xmax>
			<ymax>147</ymax>
		</bndbox>
	</object>
</annotation>